{
    "District": "moga",
    "data": [
        {
            "Year": "2017",
            "Month": "1",
            "Avg_Temp": "12.72258064516129",
            "Avg_Dew": "9.425806451612903",
            "Avg_Humidity": "82.28387096774195",
            "Avg_Precipitation": "3.064516129032258"
        },
        {
            "Year": "2017",
            "Month": "2",
            "Avg_Temp": "16.803571428571427",
            "Avg_Dew": "10.267857142857142",
            "Avg_Humidity": "70.03928571428571",
            "Avg_Precipitation": "0.19642857142857142"
        },
        {
            "Year": "2017",
            "Month": "3",
            "Avg_Temp": "21.548387096774192",
            "Avg_Dew": "11.0",
            "Avg_Humidity": "56.92258064516129",
            "Avg_Precipitation": "1.1290322580645162"
        },
        {
            "Year": "2017",
            "Month": "4",
            "Avg_Temp": "30.09",
            "Avg_Dew": "11.563333333333333",
            "Avg_Humidity": "36.45666666666667",
            "Avg_Precipitation": "0.44000000000000006"
        },
        {
            "Year": "2017",
            "Month": "5",
            "Avg_Temp": "33.145161290322584",
            "Avg_Dew": "15.841935483870968",
            "Avg_Humidity": "38.31935483870968",
            "Avg_Precipitation": "0.9225806451612902"
        },
        {
            "Year": "2017",
            "Month": "6",
            "Avg_Temp": "32.14",
            "Avg_Dew": "21.459999999999997",
            "Avg_Humidity": "57.85333333333333",
            "Avg_Precipitation": "5.92"
        },
        {
            "Year": "2017",
            "Month": "7",
            "Avg_Temp": "31.009677419354837",
            "Avg_Dew": "26.287096774193547",
            "Avg_Humidity": "76.84516129032258",
            "Avg_Precipitation": "7.541935483870968"
        },
        {
            "Year": "2017",
            "Month": "8",
            "Avg_Temp": "30.293548387096774",
            "Avg_Dew": "26.41290322580645",
            "Avg_Humidity": "80.59677419354838",
            "Avg_Precipitation": "3.067741935483871"
        },
        {
            "Year": "2017",
            "Month": "9",
            "Avg_Temp": "28.903333333333332",
            "Avg_Dew": "23.65",
            "Avg_Humidity": "75.36666666666666",
            "Avg_Precipitation": "1.7166666666666666"
        },
        {
            "Year": "2017",
            "Month": "10",
            "Avg_Temp": "25.822580645161292",
            "Avg_Dew": "18.048387096774192",
            "Avg_Humidity": "65.29677419354839",
            "Avg_Precipitation": "0.05806451612903226"
        },
        {
            "Year": "2017",
            "Month": "11",
            "Avg_Temp": "17.796666666666667",
            "Avg_Dew": "12.93",
            "Avg_Humidity": "75.98",
            "Avg_Precipitation": "0.30333333333333334"
        },
        {
            "Year": "2017",
            "Month": "12",
            "Avg_Temp": "13.96774193548387",
            "Avg_Dew": "8.516129032258064",
            "Avg_Humidity": "72.74193548387096",
            "Avg_Precipitation": "0.6580645161290323"
        },
        {
            "Year": "2018",
            "Month": "1",
            "Avg_Temp": "12.280645161290321",
            "Avg_Dew": "7.787096774193548",
            "Avg_Humidity": "76.99354838709678",
            "Avg_Precipitation": "0.47419354838709676"
        },
        {
            "Year": "2018",
            "Month": "2",
            "Avg_Temp": "16.228571428571428",
            "Avg_Dew": "9.828571428571427",
            "Avg_Humidity": "69.29285714285714",
            "Avg_Precipitation": "0.7321428571428571"
        },
        {
            "Year": "2018",
            "Month": "3",
            "Avg_Temp": "22.612903225806452",
            "Avg_Dew": "13.670967741935485",
            "Avg_Humidity": "60.83870967741935",
            "Avg_Precipitation": "0.3967741935483871"
        },
        {
            "Year": "2018",
            "Month": "4",
            "Avg_Temp": "28.353333333333335",
            "Avg_Dew": "14.726666666666667",
            "Avg_Humidity": "48.156666666666666",
            "Avg_Precipitation": "0.85"
        },
        {
            "Year": "2018",
            "Month": "5",
            "Avg_Temp": "32.75806451612903",
            "Avg_Dew": "13.948387096774193",
            "Avg_Humidity": "36.08387096774193",
            "Avg_Precipitation": "0.7225806451612903"
        },
        {
            "Year": "2018",
            "Month": "6",
            "Avg_Temp": "33.440000000000005",
            "Avg_Dew": "21.616666666666667",
            "Avg_Humidity": "53.336666666666666",
            "Avg_Precipitation": "2.7199999999999998"
        },
        {
            "Year": "2018",
            "Month": "7",
            "Avg_Temp": "30.47741935483871",
            "Avg_Dew": "26.096774193548388",
            "Avg_Humidity": "78.57741935483871",
            "Avg_Precipitation": "8.270967741935483"
        },
        {
            "Year": "2018",
            "Month": "8",
            "Avg_Temp": "30.151612903225807",
            "Avg_Dew": "26.496774193548386",
            "Avg_Humidity": "81.64516129032258",
            "Avg_Precipitation": "3.667741935483871"
        },
        {
            "Year": "2018",
            "Month": "9",
            "Avg_Temp": "27.84333333333333",
            "Avg_Dew": "23.973333333333336",
            "Avg_Humidity": "80.77",
            "Avg_Precipitation": "8.683333333333334"
        },
        {
            "Year": "2018",
            "Month": "10",
            "Avg_Temp": "24.05483870967742",
            "Avg_Dew": "17.63225806451613",
            "Avg_Humidity": "70.2741935483871",
            "Avg_Precipitation": "0.0967741935483871"
        },
        {
            "Year": "2018",
            "Month": "11",
            "Avg_Temp": "18.706666666666667",
            "Avg_Dew": "12.379999999999999",
            "Avg_Humidity": "70.01333333333334",
            "Avg_Precipitation": "0.6566666666666666"
        },
        {
            "Year": "2018",
            "Month": "12",
            "Avg_Temp": "12.683870967741935",
            "Avg_Dew": "8.283870967741937",
            "Avg_Humidity": "77.54838709677419",
            "Avg_Precipitation": "0.870967741935484"
        },
        {
            "Year": "2019",
            "Month": "1",
            "Avg_Temp": "11.616129032258065",
            "Avg_Dew": "7.696774193548387",
            "Avg_Humidity": "79.26774193548388",
            "Avg_Precipitation": "2.864516129032258"
        },
        {
            "Year": "2019",
            "Month": "2",
            "Avg_Temp": "14.189285714285715",
            "Avg_Dew": "10.664285714285715",
            "Avg_Humidity": "81.07857142857142",
            "Avg_Precipitation": "3.8"
        },
        {
            "Year": "2019",
            "Month": "3",
            "Avg_Temp": "18.983870967741936",
            "Avg_Dew": "12.62258064516129",
            "Avg_Humidity": "69.86451612903227",
            "Avg_Precipitation": "0.8064516129032258"
        },
        {
            "Year": "2019",
            "Month": "4",
            "Avg_Temp": "27.23",
            "Avg_Dew": "16.106666666666666",
            "Avg_Humidity": "55.169999999999995",
            "Avg_Precipitation": "2.0799999999999996"
        },
        {
            "Year": "2019",
            "Month": "5",
            "Avg_Temp": "30.51290322580645",
            "Avg_Dew": "15.070967741935483",
            "Avg_Humidity": "43.97741935483871",
            "Avg_Precipitation": "0.8967741935483872"
        },
        {
            "Year": "2019",
            "Month": "6",
            "Avg_Temp": "34.0",
            "Avg_Dew": "19.05666666666667",
            "Avg_Humidity": "45.276666666666664",
            "Avg_Precipitation": "0.65"
        },
        {
            "Year": "2019",
            "Month": "7",
            "Avg_Temp": "30.61935483870968",
            "Avg_Dew": "25.41290322580645",
            "Avg_Humidity": "75.39354838709677",
            "Avg_Precipitation": "5.464516129032258"
        },
        {
            "Year": "2019",
            "Month": "8",
            "Avg_Temp": "29.958064516129035",
            "Avg_Dew": "26.36774193548387",
            "Avg_Humidity": "81.81935483870969",
            "Avg_Precipitation": "5.829032258064516"
        },
        {
            "Year": "2019",
            "Month": "9",
            "Avg_Temp": "29.41",
            "Avg_Dew": "25.426666666666666",
            "Avg_Humidity": "80.04333333333334",
            "Avg_Precipitation": "1.4366666666666668"
        },
        {
            "Year": "2019",
            "Month": "10",
            "Avg_Temp": "25.061290322580643",
            "Avg_Dew": "18.374193548387098",
            "Avg_Humidity": "68.93870967741935",
            "Avg_Precipitation": "0.10967741935483873"
        },
        {
            "Year": "2019",
            "Month": "11",
            "Avg_Temp": "19.37",
            "Avg_Dew": "13.896666666666667",
            "Avg_Humidity": "73.11999999999999",
            "Avg_Precipitation": "1.6333333333333333"
        },
        {
            "Year": "2019",
            "Month": "12",
            "Avg_Temp": "11.3",
            "Avg_Dew": "8.574193548387097",
            "Avg_Humidity": "85.10645161290323",
            "Avg_Precipitation": "0.7258064516129032"
        },
        {
            "Year": "2020",
            "Month": "1",
            "Avg_Temp": "11.174193548387096",
            "Avg_Dew": "8.216129032258063",
            "Avg_Humidity": "83.61290322580645",
            "Avg_Precipitation": "1.467741935483871"
        },
        {
            "Year": "2020",
            "Month": "2",
            "Avg_Temp": "15.39655172413793",
            "Avg_Dew": "10.348275862068967",
            "Avg_Humidity": "74.50344827586207",
            "Avg_Precipitation": "1.7517241379310344"
        },
        {
            "Year": "2020",
            "Month": "3",
            "Avg_Temp": "19.154838709677417",
            "Avg_Dew": "14.52258064516129",
            "Avg_Humidity": "76.65806451612903",
            "Avg_Precipitation": "3.9935483870967743"
        },
        {
            "Year": "2020",
            "Month": "4",
            "Avg_Temp": "25.726666666666667",
            "Avg_Dew": "15.863333333333333",
            "Avg_Humidity": "58.52333333333333",
            "Avg_Precipitation": "0.99"
        },
        {
            "Year": "2020",
            "Month": "5",
            "Avg_Temp": "30.364516129032257",
            "Avg_Dew": "16.86774193548387",
            "Avg_Humidity": "48.87419354838709",
            "Avg_Precipitation": "2.138709677419355"
        },
        {
            "Year": "2020",
            "Month": "6",
            "Avg_Temp": "31.866666666666667",
            "Avg_Dew": "22.793333333333333",
            "Avg_Humidity": "60.86333333333334",
            "Avg_Precipitation": "0.6266666666666667"
        },
        {
            "Year": "2020",
            "Month": "7",
            "Avg_Temp": "30.9258064516129",
            "Avg_Dew": "25.887096774193548",
            "Avg_Humidity": "75.78387096774195",
            "Avg_Precipitation": "4.283870967741936"
        },
        {
            "Year": "2020",
            "Month": "8",
            "Avg_Temp": "30.248387096774195",
            "Avg_Dew": "26.65806451612903",
            "Avg_Humidity": "81.76451612903227",
            "Avg_Precipitation": "4.351612903225806"
        },
        {
            "Year": "2020",
            "Month": "9",
            "Avg_Temp": "30.403333333333332",
            "Avg_Dew": "24.05",
            "Avg_Humidity": "70.83999999999999",
            "Avg_Precipitation": "1.9033333333333333"
        },
        {
            "Year": "2020",
            "Month": "10",
            "Avg_Temp": "25.07741935483871",
            "Avg_Dew": "14.725806451612904",
            "Avg_Humidity": "56.400000000000006",
            "Avg_Precipitation": "0.02903225806451613"
        },
        {
            "Year": "2020",
            "Month": "11",
            "Avg_Temp": "17.473333333333336",
            "Avg_Dew": "10.413333333333332",
            "Avg_Humidity": "67.20333333333333",
            "Avg_Precipitation": "0.8766666666666667"
        },
        {
            "Year": "2020",
            "Month": "12",
            "Avg_Temp": "12.62258064516129",
            "Avg_Dew": "8.764516129032257",
            "Avg_Humidity": "79.84516129032258",
            "Avg_Precipitation": "0.4419354838709677"
        }
    ]
}